[{"content":"fasasa\n","permalink":"http://localhost:1313/post/111/","summary":"\u003cp\u003efasasa\u003c/p\u003e","title":"111"},{"content":"你好，hugofafafafa\n","permalink":"http://localhost:1313/post/test/","summary":"\u003cp\u003e你好，hugofafafafa\u003c/p\u003e","title":"hello,hugo"},{"content":"你好，hugo1111a fa fapfa fq af a\n","permalink":"http://localhost:1313/post/test02/","summary":"\u003cp\u003e你好，hugo1111a fa fapfa fq af a\u003c/p\u003e","title":"hello,hugo"},{"content":"阿发；放假阿发；啊\n","permalink":"http://localhost:1313/post/process/","summary":"\u003cp\u003e阿发；放假阿发；啊\u003c/p\u003e","title":"process"},{"content":"fafaf\n","permalink":"http://localhost:1313/post/test03/","summary":"\u003cp\u003efafaf\u003c/p\u003e","title":"test03"},{"content":"afafa\nfaaa\n","permalink":"http://localhost:1313/post/trd/","summary":"\u003cp\u003eafafa\u003c/p\u003e\n\u003cp\u003efaaa\u003c/p\u003e","title":"trd"},{"content":"fhafha;fa\n","permalink":"http://localhost:1313/post/%E5%85%A8%E6%B5%81%E7%A8%8B/","summary":"\u003cp\u003efhafha;fa\u003c/p\u003e","title":"全流程"},{"content":"111\n","permalink":"http://localhost:1313/post/2025-03-13-build-til-blog-by-hugo/","summary":"\u003cp\u003e111\u003c/p\u003e","title":"从零开始使用 Hugo 搭建 TIL 博客"},{"content":"fafafaf\n","permalink":"http://localhost:1313/post/555/","summary":"\u003cp\u003efafafaf\u003c/p\u003e","title":"555"},{"content":"faasdfhafuafpaweofuapweuf\nca;hfaf\n","permalink":"http://localhost:1313/post/hfafha/","summary":"\u003cp\u003efaasdfhafuafpaweofuapweuf\u003c/p\u003e\n\u003cp\u003eca;hfaf\u003c/p\u003e","title":"hfafha"},{"content":"fasasa\n","permalink":"http://localhost:1313/post/111/","summary":"\u003cp\u003efasasa\u003c/p\u003e","title":"111"},{"content":"你好，hugofafafafa\n","permalink":"http://localhost:1313/post/test/","summary":"\u003cp\u003e你好，hugofafafafa\u003c/p\u003e","title":"hello,hugo"},{"content":"你好，hugo1111a fa fapfa fq af a\n","permalink":"http://localhost:1313/post/test02/","summary":"\u003cp\u003e你好，hugo1111a fa fapfa fq af a\u003c/p\u003e","title":"hello,hugo"},{"content":"阿发；放假阿发；啊\n","permalink":"http://localhost:1313/post/process/","summary":"\u003cp\u003e阿发；放假阿发；啊\u003c/p\u003e","title":"process"},{"content":"fafaf\n","permalink":"http://localhost:1313/post/test03/","summary":"\u003cp\u003efafaf\u003c/p\u003e","title":"test03"},{"content":"afafa\nfaaa\n","permalink":"http://localhost:1313/post/trd/","summary":"\u003cp\u003eafafa\u003c/p\u003e\n\u003cp\u003efaaa\u003c/p\u003e","title":"trd"},{"content":"fhafha;fa\n","permalink":"http://localhost:1313/post/%E5%85%A8%E6%B5%81%E7%A8%8B/","summary":"\u003cp\u003efhafha;fa\u003c/p\u003e","title":"全流程"},{"content":"111\n","permalink":"http://localhost:1313/post/2025-03-13-build-til-blog-by-hugo/","summary":"\u003cp\u003e111\u003c/p\u003e","title":"从零开始使用 Hugo 搭建 TIL 博客"},{"content":"fafafaf\n","permalink":"http://localhost:1313/post/555/","summary":"\u003cp\u003efafafaf\u003c/p\u003e","title":"555"},{"content":"faasdfhafuafpaweofuapweuf\nca;hfaf\n","permalink":"http://localhost:1313/post/hfafha/","summary":"\u003cp\u003efaasdfhafuafpaweofuapweuf\u003c/p\u003e\n\u003cp\u003eca;hfaf\u003c/p\u003e","title":"hfafha"},{"content":"fasasa\n","permalink":"http://localhost:1313/post/111/","summary":"\u003cp\u003efasasa\u003c/p\u003e","title":"111"},{"content":"你好，hugofafafafa\n","permalink":"http://localhost:1313/post/test/","summary":"\u003cp\u003e你好，hugofafafafa\u003c/p\u003e","title":"hello,hugo"},{"content":"你好，hugo1111a fa fapfa fq af a\n","permalink":"http://localhost:1313/post/test02/","summary":"\u003cp\u003e你好，hugo1111a fa fapfa fq af a\u003c/p\u003e","title":"hello,hugo"},{"content":"阿发；放假阿发；啊\n","permalink":"http://localhost:1313/post/process/","summary":"\u003cp\u003e阿发；放假阿发；啊\u003c/p\u003e","title":"process"},{"content":"fafaf\n","permalink":"http://localhost:1313/post/test03/","summary":"\u003cp\u003efafaf\u003c/p\u003e","title":"test03"},{"content":"afafa\nfaaa\n","permalink":"http://localhost:1313/post/trd/","summary":"\u003cp\u003eafafa\u003c/p\u003e\n\u003cp\u003efaaa\u003c/p\u003e","title":"trd"},{"content":"fhafha;fa\n","permalink":"http://localhost:1313/post/%E5%85%A8%E6%B5%81%E7%A8%8B/","summary":"\u003cp\u003efhafha;fa\u003c/p\u003e","title":"全流程"},{"content":"111\n","permalink":"http://localhost:1313/post/2025-03-13-build-til-blog-by-hugo/","summary":"\u003cp\u003e111\u003c/p\u003e","title":"从零开始使用 Hugo 搭建 TIL 博客"},{"content":"fafafaf\n","permalink":"http://localhost:1313/post/555/","summary":"\u003cp\u003efafafaf\u003c/p\u003e","title":"555"},{"content":"faasdfhafuafpaweofuapweuf\nca;hfaf\n","permalink":"http://localhost:1313/post/hfafha/","summary":"\u003cp\u003efaasdfhafuafpaweofuapweuf\u003c/p\u003e\n\u003cp\u003eca;hfaf\u003c/p\u003e","title":"hfafha"},{"content":"fasasa\n","permalink":"http://localhost:1313/post/111/","summary":"\u003cp\u003efasasa\u003c/p\u003e","title":"111"},{"content":"你好，hugofafafafa\n","permalink":"http://localhost:1313/post/test/","summary":"\u003cp\u003e你好，hugofafafafa\u003c/p\u003e","title":"hello,hugo"},{"content":"你好，hugo1111a fa fapfa fq af a\n","permalink":"http://localhost:1313/post/test02/","summary":"\u003cp\u003e你好，hugo1111a fa fapfa fq af a\u003c/p\u003e","title":"hello,hugo"},{"content":"阿发；放假阿发；啊\n","permalink":"http://localhost:1313/post/process/","summary":"\u003cp\u003e阿发；放假阿发；啊\u003c/p\u003e","title":"process"},{"content":"fafaf\n","permalink":"http://localhost:1313/post/test03/","summary":"\u003cp\u003efafaf\u003c/p\u003e","title":"test03"},{"content":"afafa\nfaaa\n","permalink":"http://localhost:1313/post/trd/","summary":"\u003cp\u003eafafa\u003c/p\u003e\n\u003cp\u003efaaa\u003c/p\u003e","title":"trd"},{"content":"fhafha;fa\n","permalink":"http://localhost:1313/post/%E5%85%A8%E6%B5%81%E7%A8%8B/","summary":"\u003cp\u003efhafha;fa\u003c/p\u003e","title":"全流程"},{"content":"111\n","permalink":"http://localhost:1313/post/2025-03-13-build-til-blog-by-hugo/","summary":"\u003cp\u003e111\u003c/p\u003e","title":"从零开始使用 Hugo 搭建 TIL 博客"},{"content":"fafafaf\n","permalink":"http://localhost:1313/post/555/","summary":"\u003cp\u003efafafaf\u003c/p\u003e","title":"555"},{"content":"faasdfhafuafpaweofuapweuf\nca;hfaf\n","permalink":"http://localhost:1313/post/hfafha/","summary":"\u003cp\u003efaasdfhafuafpaweofuapweuf\u003c/p\u003e\n\u003cp\u003eca;hfaf\u003c/p\u003e","title":"hfafha"},{"content":"fasasa\n","permalink":"http://localhost:1313/post/111/","summary":"\u003cp\u003efasasa\u003c/p\u003e","title":"111"},{"content":"你好，hugofafafafa\n","permalink":"http://localhost:1313/post/test/","summary":"\u003cp\u003e你好，hugofafafafa\u003c/p\u003e","title":"hello,hugo"},{"content":"你好，hugo1111a fa fapfa fq af a\n","permalink":"http://localhost:1313/post/test02/","summary":"\u003cp\u003e你好，hugo1111a fa fapfa fq af a\u003c/p\u003e","title":"hello,hugo"},{"content":"阿发；放假阿发；啊\n","permalink":"http://localhost:1313/post/process/","summary":"\u003cp\u003e阿发；放假阿发；啊\u003c/p\u003e","title":"process"},{"content":"fafaf\n","permalink":"http://localhost:1313/post/test03/","summary":"\u003cp\u003efafaf\u003c/p\u003e","title":"test03"},{"content":"afafa\nfaaa\n","permalink":"http://localhost:1313/post/trd/","summary":"\u003cp\u003eafafa\u003c/p\u003e\n\u003cp\u003efaaa\u003c/p\u003e","title":"trd"},{"content":"fhafha;fa\n","permalink":"http://localhost:1313/post/%E5%85%A8%E6%B5%81%E7%A8%8B/","summary":"\u003cp\u003efhafha;fa\u003c/p\u003e","title":"全流程"},{"content":"111\n","permalink":"http://localhost:1313/post/2025-03-13-build-til-blog-by-hugo/","summary":"\u003cp\u003e111\u003c/p\u003e","title":"从零开始使用 Hugo 搭建 TIL 博客"},{"content":"fafafaf\n","permalink":"http://localhost:1313/post/555/","summary":"\u003cp\u003efafafaf\u003c/p\u003e","title":"555"},{"content":"faasdfhafuafpaweofuapweuf\nca;hfaf\n","permalink":"http://localhost:1313/post/hfafha/","summary":"\u003cp\u003efaasdfhafuafpaweofuapweuf\u003c/p\u003e\n\u003cp\u003eca;hfaf\u003c/p\u003e","title":"hfafha"},{"content":"fasasa\n","permalink":"http://localhost:1313/post/111/","summary":"\u003cp\u003efasasa\u003c/p\u003e","title":"111"},{"content":"你好，hugofafafafa\n","permalink":"http://localhost:1313/post/test/","summary":"\u003cp\u003e你好，hugofafafafa\u003c/p\u003e","title":"hello,hugo"},{"content":"你好，hugo1111a fa fapfa fq af a\n","permalink":"http://localhost:1313/post/test02/","summary":"\u003cp\u003e你好，hugo1111a fa fapfa fq af a\u003c/p\u003e","title":"hello,hugo"},{"content":"阿发；放假阿发；啊\n","permalink":"http://localhost:1313/post/process/","summary":"\u003cp\u003e阿发；放假阿发；啊\u003c/p\u003e","title":"process"},{"content":"fafaf\n","permalink":"http://localhost:1313/post/test03/","summary":"\u003cp\u003efafaf\u003c/p\u003e","title":"test03"},{"content":"afafa\nfaaa\n","permalink":"http://localhost:1313/post/trd/","summary":"\u003cp\u003eafafa\u003c/p\u003e\n\u003cp\u003efaaa\u003c/p\u003e","title":"trd"},{"content":"fhafha;fa\n","permalink":"http://localhost:1313/post/%E5%85%A8%E6%B5%81%E7%A8%8B/","summary":"\u003cp\u003efhafha;fa\u003c/p\u003e","title":"全流程"},{"content":"111\n","permalink":"http://localhost:1313/post/2025-03-13-build-til-blog-by-hugo/","summary":"\u003cp\u003e111\u003c/p\u003e","title":"从零开始使用 Hugo 搭建 TIL 博客"},{"content":"fafafaf\n","permalink":"http://localhost:1313/post/555/","summary":"\u003cp\u003efafafaf\u003c/p\u003e","title":"555"},{"content":"faasdfhafuafpaweofuapweuf\nca;hfaf\n","permalink":"http://localhost:1313/post/hfafha/","summary":"\u003cp\u003efaasdfhafuafpaweofuapweuf\u003c/p\u003e\n\u003cp\u003eca;hfaf\u003c/p\u003e","title":"hfafha"},{"content":"fasasa\n","permalink":"http://localhost:1313/post/111/","summary":"\u003cp\u003efasasa\u003c/p\u003e","title":"111"},{"content":"你好，hugofafafafa\n","permalink":"http://localhost:1313/post/test/","summary":"\u003cp\u003e你好，hugofafafafa\u003c/p\u003e","title":"hello,hugo"},{"content":"你好，hugo1111a fa fapfa fq af a\n","permalink":"http://localhost:1313/post/test02/","summary":"\u003cp\u003e你好，hugo1111a fa fapfa fq af a\u003c/p\u003e","title":"hello,hugo"},{"content":"阿发；放假阿发；啊\n","permalink":"http://localhost:1313/post/process/","summary":"\u003cp\u003e阿发；放假阿发；啊\u003c/p\u003e","title":"process"},{"content":"fafaf\n","permalink":"http://localhost:1313/post/test03/","summary":"\u003cp\u003efafaf\u003c/p\u003e","title":"test03"},{"content":"afafa\nfaaa\n","permalink":"http://localhost:1313/post/trd/","summary":"\u003cp\u003eafafa\u003c/p\u003e\n\u003cp\u003efaaa\u003c/p\u003e","title":"trd"},{"content":"fhafha;fa\n","permalink":"http://localhost:1313/post/%E5%85%A8%E6%B5%81%E7%A8%8B/","summary":"\u003cp\u003efhafha;fa\u003c/p\u003e","title":"全流程"},{"content":"111\n","permalink":"http://localhost:1313/post/2025-03-13-build-til-blog-by-hugo/","summary":"\u003cp\u003e111\u003c/p\u003e","title":"从零开始使用 Hugo 搭建 TIL 博客"},{"content":"fafafaf\n","permalink":"http://localhost:1313/post/555/","summary":"\u003cp\u003efafafaf\u003c/p\u003e","title":"555"},{"content":"faasdfhafuafpaweofuapweuf\nca;hfaf\n","permalink":"http://localhost:1313/post/hfafha/","summary":"\u003cp\u003efaasdfhafuafpaweofuapweuf\u003c/p\u003e\n\u003cp\u003eca;hfaf\u003c/p\u003e","title":"hfafha"},{"content":"fasasa\n","permalink":"http://localhost:1313/post/111/","summary":"\u003cp\u003efasasa\u003c/p\u003e","title":"111"},{"content":"你好，hugofafafafa\n","permalink":"http://localhost:1313/post/test/","summary":"\u003cp\u003e你好，hugofafafafa\u003c/p\u003e","title":"hello,hugo"},{"content":"你好，hugo1111a fa fapfa fq af a\n","permalink":"http://localhost:1313/post/test02/","summary":"\u003cp\u003e你好，hugo1111a fa fapfa fq af a\u003c/p\u003e","title":"hello,hugo"},{"content":"阿发；放假阿发；啊\n","permalink":"http://localhost:1313/post/process/","summary":"\u003cp\u003e阿发；放假阿发；啊\u003c/p\u003e","title":"process"},{"content":"fafaf\n","permalink":"http://localhost:1313/post/test03/","summary":"\u003cp\u003efafaf\u003c/p\u003e","title":"test03"},{"content":"afafa\nfaaa\n","permalink":"http://localhost:1313/post/trd/","summary":"\u003cp\u003eafafa\u003c/p\u003e\n\u003cp\u003efaaa\u003c/p\u003e","title":"trd"},{"content":"fhafha;fa\n","permalink":"http://localhost:1313/post/%E5%85%A8%E6%B5%81%E7%A8%8B/","summary":"\u003cp\u003efhafha;fa\u003c/p\u003e","title":"全流程"},{"content":"111\n","permalink":"http://localhost:1313/post/2025-03-13-build-til-blog-by-hugo/","summary":"\u003cp\u003e111\u003c/p\u003e","title":"从零开始使用 Hugo 搭建 TIL 博客"},{"content":"fafafaf\n","permalink":"http://localhost:1313/post/555/","summary":"\u003cp\u003efafafaf\u003c/p\u003e","title":"555"},{"content":"faasdfhafuafpaweofuapweuf\nca;hfaf\n","permalink":"http://localhost:1313/post/hfafha/","summary":"\u003cp\u003efaasdfhafuafpaweofuapweuf\u003c/p\u003e\n\u003cp\u003eca;hfaf\u003c/p\u003e","title":"hfafha"},{"content":"fasasa\n","permalink":"http://localhost:1313/post/111/","summary":"\u003cp\u003efasasa\u003c/p\u003e","title":"111"},{"content":"你好，hugofafafafa\n","permalink":"http://localhost:1313/post/test/","summary":"\u003cp\u003e你好，hugofafafafa\u003c/p\u003e","title":"hello,hugo"},{"content":"你好，hugo1111a fa fapfa fq af a\n","permalink":"http://localhost:1313/post/test02/","summary":"\u003cp\u003e你好，hugo1111a fa fapfa fq af a\u003c/p\u003e","title":"hello,hugo"},{"content":"阿发；放假阿发；啊\n","permalink":"http://localhost:1313/post/process/","summary":"\u003cp\u003e阿发；放假阿发；啊\u003c/p\u003e","title":"process"},{"content":"fafaf\n","permalink":"http://localhost:1313/post/test03/","summary":"\u003cp\u003efafaf\u003c/p\u003e","title":"test03"},{"content":"afafa\nfaaa\n","permalink":"http://localhost:1313/post/trd/","summary":"\u003cp\u003eafafa\u003c/p\u003e\n\u003cp\u003efaaa\u003c/p\u003e","title":"trd"},{"content":"fhafha;fa\n","permalink":"http://localhost:1313/post/%E5%85%A8%E6%B5%81%E7%A8%8B/","summary":"\u003cp\u003efhafha;fa\u003c/p\u003e","title":"全流程"},{"content":"111\n","permalink":"http://localhost:1313/post/2025-03-13-build-til-blog-by-hugo/","summary":"\u003cp\u003e111\u003c/p\u003e","title":"从零开始使用 Hugo 搭建 TIL 博客"},{"content":"fafafaf\n","permalink":"http://localhost:1313/post/555/","summary":"\u003cp\u003efafafaf\u003c/p\u003e","title":"555"},{"content":"faasdfhafuafpaweofuapweuf\nca;hfaf\n","permalink":"http://localhost:1313/post/hfafha/","summary":"\u003cp\u003efaasdfhafuafpaweofuapweuf\u003c/p\u003e\n\u003cp\u003eca;hfaf\u003c/p\u003e","title":"hfafha"},{"content":"fasasa\n","permalink":"http://localhost:1313/post/111/","summary":"\u003cp\u003efasasa\u003c/p\u003e","title":"111"},{"content":"你好，hugofafafafa\n","permalink":"http://localhost:1313/post/test/","summary":"\u003cp\u003e你好，hugofafafafa\u003c/p\u003e","title":"hello,hugo"},{"content":"你好，hugo1111a fa fapfa fq af a\n","permalink":"http://localhost:1313/post/test02/","summary":"\u003cp\u003e你好，hugo1111a fa fapfa fq af a\u003c/p\u003e","title":"hello,hugo"},{"content":"阿发；放假阿发；啊\n","permalink":"http://localhost:1313/post/process/","summary":"\u003cp\u003e阿发；放假阿发；啊\u003c/p\u003e","title":"process"},{"content":"fafaf\n","permalink":"http://localhost:1313/post/test03/","summary":"\u003cp\u003efafaf\u003c/p\u003e","title":"test03"},{"content":"afafa\nfaaa\n","permalink":"http://localhost:1313/post/trd/","summary":"\u003cp\u003eafafa\u003c/p\u003e\n\u003cp\u003efaaa\u003c/p\u003e","title":"trd"},{"content":"fhafha;fa\n","permalink":"http://localhost:1313/post/%E5%85%A8%E6%B5%81%E7%A8%8B/","summary":"\u003cp\u003efhafha;fa\u003c/p\u003e","title":"全流程"},{"content":"111\n","permalink":"http://localhost:1313/post/2025-03-13-build-til-blog-by-hugo/","summary":"\u003cp\u003e111\u003c/p\u003e","title":"从零开始使用 Hugo 搭建 TIL 博客"},{"content":"fafafaf\n","permalink":"http://localhost:1313/post/555/","summary":"\u003cp\u003efafafaf\u003c/p\u003e","title":"555"},{"content":"faasdfhafuafpaweofuapweuf\nca;hfaf\n","permalink":"http://localhost:1313/post/hfafha/","summary":"\u003cp\u003efaasdfhafuafpaweofuapweuf\u003c/p\u003e\n\u003cp\u003eca;hfaf\u003c/p\u003e","title":"hfafha"},{"content":"fasasa\n","permalink":"http://localhost:1313/post/111/","summary":"\u003cp\u003efasasa\u003c/p\u003e","title":"111"},{"content":"你好，hugofafafafa\n","permalink":"http://localhost:1313/post/test/","summary":"\u003cp\u003e你好，hugofafafafa\u003c/p\u003e","title":"hello,hugo"},{"content":"你好，hugo1111a fa fapfa fq af a\n","permalink":"http://localhost:1313/post/test02/","summary":"\u003cp\u003e你好，hugo1111a fa fapfa fq af a\u003c/p\u003e","title":"hello,hugo"},{"content":"阿发；放假阿发；啊\n","permalink":"http://localhost:1313/post/process/","summary":"\u003cp\u003e阿发；放假阿发；啊\u003c/p\u003e","title":"process"},{"content":"fafaf\n","permalink":"http://localhost:1313/post/test03/","summary":"\u003cp\u003efafaf\u003c/p\u003e","title":"test03"},{"content":"afafa\nfaaa\n","permalink":"http://localhost:1313/post/trd/","summary":"\u003cp\u003eafafa\u003c/p\u003e\n\u003cp\u003efaaa\u003c/p\u003e","title":"trd"},{"content":"fhafha;fa\n","permalink":"http://localhost:1313/post/%E5%85%A8%E6%B5%81%E7%A8%8B/","summary":"\u003cp\u003efhafha;fa\u003c/p\u003e","title":"全流程"},{"content":"111\n","permalink":"http://localhost:1313/post/2025-03-13-build-til-blog-by-hugo/","summary":"\u003cp\u003e111\u003c/p\u003e","title":"从零开始使用 Hugo 搭建 TIL 博客"},{"content":"fafafaf\n","permalink":"http://localhost:1313/post/555/","summary":"\u003cp\u003efafafaf\u003c/p\u003e","title":"555"},{"content":"faasdfhafuafpaweofuapweuf\nca;hfaf\n","permalink":"http://localhost:1313/post/hfafha/","summary":"\u003cp\u003efaasdfhafuafpaweofuapweuf\u003c/p\u003e\n\u003cp\u003eca;hfaf\u003c/p\u003e","title":"hfafha"},{"content":"fasasa\n","permalink":"http://localhost:1313/post/111/","summary":"\u003cp\u003efasasa\u003c/p\u003e","title":"111"},{"content":"你好，hugofafafafa\n","permalink":"http://localhost:1313/post/test/","summary":"\u003cp\u003e你好，hugofafafafa\u003c/p\u003e","title":"hello,hugo"},{"content":"你好，hugo1111a fa fapfa fq af a\n","permalink":"http://localhost:1313/post/test02/","summary":"\u003cp\u003e你好，hugo1111a fa fapfa fq af a\u003c/p\u003e","title":"hello,hugo"},{"content":"阿发；放假阿发；啊\n","permalink":"http://localhost:1313/post/process/","summary":"\u003cp\u003e阿发；放假阿发；啊\u003c/p\u003e","title":"process"},{"content":"fafaf\n","permalink":"http://localhost:1313/post/test03/","summary":"\u003cp\u003efafaf\u003c/p\u003e","title":"test03"},{"content":"afafa\nfaaa\n","permalink":"http://localhost:1313/post/trd/","summary":"\u003cp\u003eafafa\u003c/p\u003e\n\u003cp\u003efaaa\u003c/p\u003e","title":"trd"},{"content":"fhafha;fa\n","permalink":"http://localhost:1313/post/%E5%85%A8%E6%B5%81%E7%A8%8B/","summary":"\u003cp\u003efhafha;fa\u003c/p\u003e","title":"全流程"},{"content":"111\n","permalink":"http://localhost:1313/post/2025-03-13-build-til-blog-by-hugo/","summary":"\u003cp\u003e111\u003c/p\u003e","title":"从零开始使用 Hugo 搭建 TIL 博客"},{"content":"fafafaf\n","permalink":"http://localhost:1313/post/555/","summary":"\u003cp\u003efafafaf\u003c/p\u003e","title":"555"},{"content":"faasdfhafuafpaweofuapweuf\nca;hfaf\n","permalink":"http://localhost:1313/post/hfafha/","summary":"\u003cp\u003efaasdfhafuafpaweofuapweuf\u003c/p\u003e\n\u003cp\u003eca;hfaf\u003c/p\u003e","title":"hfafha"},{"content":"你好，hugofafafafa\n","permalink":"http://localhost:1313/post/test/","summary":"\u003cp\u003e你好，hugofafafafa\u003c/p\u003e","title":"hello,hugo"},{"content":"你好，hugo1111a fa fapfa fq af a\n","permalink":"http://localhost:1313/post/test02/","summary":"\u003cp\u003e你好，hugo1111a fa fapfa fq af a\u003c/p\u003e","title":"hello,hugo"},{"content":"阿发；放假阿发；啊\n","permalink":"http://localhost:1313/post/process/","summary":"\u003cp\u003e阿发；放假阿发；啊\u003c/p\u003e","title":"process"},{"content":"fafaf\n","permalink":"http://localhost:1313/post/test03/","summary":"\u003cp\u003efafaf\u003c/p\u003e","title":"test03"},{"content":"afafa\nfaaa\n","permalink":"http://localhost:1313/post/trd/","summary":"\u003cp\u003eafafa\u003c/p\u003e\n\u003cp\u003efaaa\u003c/p\u003e","title":"trd"},{"content":"fhafha;fa\n","permalink":"http://localhost:1313/post/%E5%85%A8%E6%B5%81%E7%A8%8B/","summary":"\u003cp\u003efhafha;fa\u003c/p\u003e","title":"全流程"},{"content":"111\n","permalink":"http://localhost:1313/post/2025-03-13-build-til-blog-by-hugo/","summary":"\u003cp\u003e111\u003c/p\u003e","title":"从零开始使用 Hugo 搭建 TIL 博客"},{"content":"fafafaf\n","permalink":"http://localhost:1313/post/555/","summary":"\u003cp\u003efafafaf\u003c/p\u003e","title":"555"},{"content":"faasdfhafuafpaweofuapweuf\nca;hfaf\n","permalink":"http://localhost:1313/post/hfafha/","summary":"\u003cp\u003efaasdfhafuafpaweofuapweuf\u003c/p\u003e\n\u003cp\u003eca;hfaf\u003c/p\u003e","title":"hfafha"},{"content":"你好，hugofafafafa\n","permalink":"http://localhost:1313/post/test/","summary":"\u003cp\u003e你好，hugofafafafa\u003c/p\u003e","title":"hello,hugo"},{"content":"你好，hugo1111a fa fapfa fq af a\n","permalink":"http://localhost:1313/post/test02/","summary":"\u003cp\u003e你好，hugo1111a fa fapfa fq af a\u003c/p\u003e","title":"hello,hugo"},{"content":"阿发；放假阿发；啊\n","permalink":"http://localhost:1313/post/process/","summary":"\u003cp\u003e阿发；放假阿发；啊\u003c/p\u003e","title":"process"},{"content":"fafaf\n","permalink":"http://localhost:1313/post/test03/","summary":"\u003cp\u003efafaf\u003c/p\u003e","title":"test03"},{"content":"afafa\nfaaa\n","permalink":"http://localhost:1313/post/trd/","summary":"\u003cp\u003eafafa\u003c/p\u003e\n\u003cp\u003efaaa\u003c/p\u003e","title":"trd"},{"content":"fhafha;fa\n","permalink":"http://localhost:1313/post/%E5%85%A8%E6%B5%81%E7%A8%8B/","summary":"\u003cp\u003efhafha;fa\u003c/p\u003e","title":"全流程"},{"content":"111\n","permalink":"http://localhost:1313/post/2025-03-13-build-til-blog-by-hugo/","summary":"\u003cp\u003e111\u003c/p\u003e","title":"从零开始使用 Hugo 搭建 TIL 博客"},{"content":"faasdfhafuafpaweofuapweuf\nca;hfaf\n","permalink":"http://localhost:1313/post/hfafha/","summary":"\u003cp\u003efaasdfhafuafpaweofuapweuf\u003c/p\u003e\n\u003cp\u003eca;hfaf\u003c/p\u003e","title":"hfafha"},{"content":"你好，hugofafafafa\n","permalink":"http://localhost:1313/post/test/","summary":"\u003cp\u003e你好，hugofafafafa\u003c/p\u003e","title":"hello,hugo"},{"content":"你好，hugo1111a fa fapfa fq af a\n","permalink":"http://localhost:1313/post/test02/","summary":"\u003cp\u003e你好，hugo1111a fa fapfa fq af a\u003c/p\u003e","title":"hello,hugo"},{"content":"阿发；放假阿发；啊\n","permalink":"http://localhost:1313/post/process/","summary":"\u003cp\u003e阿发；放假阿发；啊\u003c/p\u003e","title":"process"},{"content":"fafaf\n","permalink":"http://localhost:1313/post/test03/","summary":"\u003cp\u003efafaf\u003c/p\u003e","title":"test03"},{"content":"afafa\nfaaa\n","permalink":"http://localhost:1313/post/trd/","summary":"\u003cp\u003eafafa\u003c/p\u003e\n\u003cp\u003efaaa\u003c/p\u003e","title":"trd"},{"content":"fhafha;fa\n","permalink":"http://localhost:1313/post/%E5%85%A8%E6%B5%81%E7%A8%8B/","summary":"\u003cp\u003efhafha;fa\u003c/p\u003e","title":"全流程"},{"content":"faasdfhafuafpaweofuapweuf\nca;hfaf\n","permalink":"http://localhost:1313/post/hfafha/","summary":"\u003cp\u003efaasdfhafuafpaweofuapweuf\u003c/p\u003e\n\u003cp\u003eca;hfaf\u003c/p\u003e","title":"hfafha"},{"content":"你好，hugofafafafa\n","permalink":"http://localhost:1313/post/test/","summary":"\u003cp\u003e你好，hugofafafafa\u003c/p\u003e","title":"hello,hugo"},{"content":"你好，hugo1111a fa fapfa fq af a\n","permalink":"http://localhost:1313/post/test02/","summary":"\u003cp\u003e你好，hugo1111a fa fapfa fq af a\u003c/p\u003e","title":"hello,hugo"},{"content":"阿发；放假阿发；啊\n","permalink":"http://localhost:1313/post/process/","summary":"\u003cp\u003e阿发；放假阿发；啊\u003c/p\u003e","title":"process"},{"content":"fafaf\n","permalink":"http://localhost:1313/post/test03/","summary":"\u003cp\u003efafaf\u003c/p\u003e","title":"test03"},{"content":"afafa\nfaaa\n","permalink":"http://localhost:1313/post/trd/","summary":"\u003cp\u003eafafa\u003c/p\u003e\n\u003cp\u003efaaa\u003c/p\u003e","title":"trd"},{"content":"faasdfhafuafpaweofuapweuf\nca;hfaf\n","permalink":"http://localhost:1313/post/hfafha/","summary":"\u003cp\u003efaasdfhafuafpaweofuapweuf\u003c/p\u003e\n\u003cp\u003eca;hfaf\u003c/p\u003e","title":"hfafha"},{"content":"你好，hugofafafafa\n","permalink":"http://localhost:1313/post/test/","summary":"\u003cp\u003e你好，hugofafafafa\u003c/p\u003e","title":"hello,hugo"},{"content":"你好，hugo1111a fa fapfa fq af a\n","permalink":"http://localhost:1313/post/test02/","summary":"\u003cp\u003e你好，hugo1111a fa fapfa fq af a\u003c/p\u003e","title":"hello,hugo"},{"content":"阿发；放假阿发；啊\n","permalink":"http://localhost:1313/post/process/","summary":"\u003cp\u003e阿发；放假阿发；啊\u003c/p\u003e","title":"process"},{"content":"fafaf\n","permalink":"http://localhost:1313/post/test03/","summary":"\u003cp\u003efafaf\u003c/p\u003e","title":"test03"},{"content":"afafa\nfaaa\n","permalink":"http://localhost:1313/post/trd/","summary":"\u003cp\u003eafafa\u003c/p\u003e\n\u003cp\u003efaaa\u003c/p\u003e","title":"trd"},{"content":"你好，hugofafafafa\n","permalink":"http://localhost:1313/post/test/","summary":"\u003cp\u003e你好，hugofafafafa\u003c/p\u003e","title":"hello,hugo"},{"content":"你好，hugo1111a fa fapfa fq af a\n","permalink":"http://localhost:1313/post/test02/","summary":"\u003cp\u003e你好，hugo1111a fa fapfa fq af a\u003c/p\u003e","title":"hello,hugo"},{"content":"fafaf\n","permalink":"http://localhost:1313/post/test03/","summary":"\u003cp\u003efafaf\u003c/p\u003e","title":"test03"},{"content":"afafa\nfaaa\n","permalink":"http://localhost:1313/post/trd/","summary":"\u003cp\u003eafafa\u003c/p\u003e\n\u003cp\u003efaaa\u003c/p\u003e","title":"trd"},{"content":"你好，hugo1111a fa fapfa fq af a\n","permalink":"http://localhost:1313/post/test02/","summary":"\u003cp\u003e你好，hugo1111a fa fapfa fq af a\u003c/p\u003e","title":"hello,hugo"},{"content":"fafaf\n","permalink":"http://localhost:1313/post/test03/","summary":"\u003cp\u003efafaf\u003c/p\u003e","title":"test03"},{"content":"afafa\nfaaa\n","permalink":"http://localhost:1313/post/trd/","summary":"\u003cp\u003eafafa\u003c/p\u003e\n\u003cp\u003efaaa\u003c/p\u003e","title":"trd"},{"content":"fafaf\n","permalink":"http://localhost:1313/post/test03/","summary":"\u003cp\u003efafaf\u003c/p\u003e","title":"test03"},{"content":"afafa\nfaaa\n","permalink":"http://localhost:1313/post/trd/","summary":"\u003cp\u003eafafa\u003c/p\u003e\n\u003cp\u003efaaa\u003c/p\u003e","title":"trd"},{"content":"afafa\nfaaa\n","permalink":"http://localhost:1313/post/trd/","summary":"\u003cp\u003eafafa\u003c/p\u003e\n\u003cp\u003efaaa\u003c/p\u003e","title":"trd"}]